source/timer.v
module timer (enable, CLK, RESET, time_seconds);

    input enable, CLK, RESET;
    output reg [6:0] time_seconds;

    always @ (posedge CLK or posedge RESET) begin
        if (RESET)
            time_seconds = 0;
        else begin
            if (enable)
                time_seconds = time_seconds + 1;
        end
    end

endmodule

source/frequency_divider.v
module frequency_divider(clk_in, RESET, clk_1hz, clk_2hz, clk_250hz, clk_1khz);
    input clk_in, RESET;
    output reg clk_1hz, clk_2hz, clk_250hz, clk_1khz;

    reg [20 : 0] cntr_1hz;
    reg [19 : 0] cntr_2hz;
    reg [17 : 0] cntr_250hz;
    reg [14 : 0] cntr_1khz;

    parameter INPUT_FREQUENCY = 1_000; // expected to be 40 000 000
    parameter TURNING_POINT_1HZ = INPUT_FREQUENCY / (1 * 2);
    parameter TURNING_POINT_2HZ = INPUT_FREQUENCY / (2 * 2);
    parameter TURNING_POINT_250HZ = INPUT_FREQUENCY / (250 * 2);
    parameter TURNING_POINT_1KHZ = INPUT_FREQUENCY / (1000 * 2);
    
    always @ (posedge clk_in or posedge RESET) begin 
        if (RESET) begin
            cntr_1hz = 0;
            cntr_2hz = 0;
            cntr_250hz = 0;
            cntr_1khz = 0;
            clk_1hz = 1'b0;
            clk_2hz = 1'b0;
            clk_250hz = 1'b0;
            clk_1khz = 1'b0;
        end
        else begin
            if (cntr_1hz > TURNING_POINT_1HZ) begin
                clk_1hz = ~clk_1hz;
                cntr_1hz = 0;
            end
            cntr_1hz = cntr_1hz + 1;

            if (cntr_2hz > TURNING_POINT_2HZ) begin
                clk_2hz = ~clk_2hz;
                cntr_2hz = 0;
            end
            cntr_2hz = cntr_2hz + 1;

            if (cntr_250hz > TURNING_POINT_250HZ) begin
                clk_250hz = ~clk_250hz;
                cntr_250hz = 0;
            end
            cntr_250hz = cntr_250hz + 1;

            if (cntr_1khz > TURNING_POINT_1KHZ) begin
                clk_1khz = ~clk_1khz;
                cntr_1khz = 0;     
            end
            cntr_1khz = cntr_1khz + 1;
        end     
    end
endmodule

test/timer_frequency_divider_test.v
`timescale 1us / 100ns

`include "../source/timer.v"
`include "../source/frequency_divider.v"

module timer_frequency_divider_test;
    reg clk_1khz;
    reg RESET;
    wire clk_1hz;
    wire clk_2hz;
    wire clk_250hz;
    wire clk_1khz_out;
    wire [6:0] time_seconds;

    frequency_divider freq_divider (clk_1khz, RESET, clk_1hz, clk_2hz, clk_250hz, clk_1khz_out);
    timer t1 (1'b1, clk_1hz, RESET, time_seconds);

    initial begin
        clk_1khz = 1'b1;
        repeat (10000) begin
            clk_1khz = ~clk_1khz; #500;
        end
    end

    initial begin
        $dumpfile("timer_frequency_divider_test.vcd");
        $dumpvars(0, timer_frequency_divider_test);
        RESET = 1'b0; #10
        RESET = 1'b1; #10
        RESET = 1'b0; #10
        $monitor("%d", time_seconds);
        // $monitor("%b", clk_1hz);
        
    end
endmodule

test/timer_frequency_divider_test.vcd
$date
	Wed Jan 08 22:50:06 2025
$end
$version
	Icarus Verilog
$end
$timescale
	100ns
$end
$scope module timer_frequency_divider_test $end
$var wire 7 ! time_seconds [6:0] $end
$var wire 1 " clk_2hz $end
$var wire 1 # clk_250hz $end
$var wire 1 $ clk_1khz_out $end
$var wire 1 % clk_1hz $end
$var reg 1 & RESET $end
$var reg 1 ' clk_1khz $end
$scope module freq_divider $end
$var wire 1 & RESET $end
$var wire 1 ' clk_in $end
$var parameter 32 ( INPUT_FREQUENCY $end
$var parameter 64 ) TURNING_POINT_1HZ $end
$var parameter 64 * TURNING_POINT_1KHZ $end
$var parameter 64 + TURNING_POINT_250HZ $end
$var parameter 64 , TURNING_POINT_2HZ $end
$var reg 1 % clk_1hz $end
$var reg 1 $ clk_1khz $end
$var reg 1 # clk_250hz $end
$var reg 1 " clk_2hz $end
$var reg 21 - cntr_1hz [20:0] $end
$var reg 15 . cntr_1khz [14:0] $end
$var reg 18 / cntr_250hz [17:0] $end
$var reg 20 0 cntr_2hz [19:0] $end
$upscope $end
$scope module t1 $end
$var wire 1 % CLK $end
$var wire 1 & RESET $end
$var wire 1 1 enable $end
$var reg 7 2 time_seconds [6:0] $end
$upscope $end
$upscope $end
$enddefinitions $end
$comment Show the parameter values. $end
$dumpall
b11111010 ,
b10 +
b0 *
b111110100 )
b1111101000 (
$end
#0
$dumpvars
bx 2
11
bx 0
bx /
bx .
bx -
0'
0&
x%
x$
x#
x"
bx !
$end
#100
0$
0#
0"
0%
b0 .
b0 /
b0 0
b0 -
b0 !
b0 2
1&
#200
0&
#5000
b1 .
b1 /
b1 0
b1 -
1'
#10000
0'
#15000
b1 .
1$
b10 /
b10 0
b10 -
1'
#20000
0'
#25000
b1 .
0$
b11 /
b11 0
b11 -
1'
#30000
0'
#35000
b1 .
1$
b1 /
1#
b100 0
b100 -
1'
#40000
0'
#45000
b1 .
0$
b10 /
b101 0
b101 -
1'
#50000
0'
#55000
b1 .
1$
b11 /
b110 0
b110 -
1'
#60000
0'
#65000
b1 .
0$
b1 /
0#
b111 0
b111 -
1'
#70000
0'
#75000
b1 .
1$
b10 /
b1000 0
b1000 -
1'
#80000
0'
#85000
b1 .
0$
b11 /
b1001 0
b1001 -
1'
#90000
0'
#95000
b1 .
1$
b1 /
1#
b1010 0
b1010 -
1'
#100000
0'
#105000
b1 .
0$
b10 /
b1011 0
b1011 -
1'
#110000
0'
#115000
b1 .
1$
b11 /
b1100 0
b1100 -
1'
#120000
0'
#125000
b1 .
0$
b1 /
0#
b1101 0
b1101 -
1'
#130000
0'
#135000
b1 .
1$
b10 /
b1110 0
b1110 -
1'
#140000
0'
#145000
b1 .
0$
b11 /
b1111 0
b1111 -
1'
#150000
0'
#155000
b1 .
1$
b1 /
1#
b10000 0
b10000 -
1'
#160000
0'
#165000
b1 .
0$
b10 /
b10001 0
b10001 -
1'
#170000
0'
#175000
b1 .
1$
b11 /
b10010 0
b10010 -
1'
#180000
0'
#185000
b1 .
0$
b1 /
0#
b10011 0
b10011 -
1'
#190000
0'
#195000
b1 .
1$
b10 /
b10100 0
b10100 -
1'
#200000
0'
#205000
b1 .
0$
b11 /
b10101 0
b10101 -
1'
#210000
0'
#215000
b1 .
1$
b1 /
1#
b10110 0
b10110 -
1'
#220000
0'
#225000
b1 .
0$
b10 /
b10111 0
b10111 -
1'
#230000
0'
#235000
b1 .
1$
b11 /
b11000 0
b11000 -
1'
#240000
0'
#245000
b1 .
0$
b1 /
0#
b11001 0
b11001 -
1'
#250000
0'
#255000
b1 .
1$
b10 /
b11010 0
b11010 -
1'
#260000
0'
#265000
b1 .
0$
b11 /
b11011 0
b11011 -
1'
#270000
0'
#275000
b1 .
1$
b1 /
1#
b11100 0
b11100 -
1'
#280000
0'
#285000
b1 .
0$
b10 /
b11101 0
b11101 -
1'
#290000
0'
#295000
b1 .
1$
b11 /
b11110 0
b11110 -
1'
#300000
0'
#305000
b1 .
0$
b1 /
0#
b11111 0
b11111 -
1'
#310000
0'
#315000
b1 .
1$
b10 /
b100000 0
b100000 -
1'
#320000
0'
#325000
b1 .
0$
b11 /
b100001 0
b100001 -
1'
#330000
0'
#335000
b1 .
1$
b1 /
1#
b100010 0
b100010 -
1'
#340000
0'
#345000
b1 .
0$
b10 /
b100011 0
b100011 -
1'
#350000
0'
#355000
b1 .
1$
b11 /
b100100 0
b100100 -
1'
#360000
0'
#365000
b1 .
0$
b1 /
0#
b100101 0
b100101 -
1'
#370000
0'
#375000
b1 .
1$
b10 /
b100110 0
b100110 -
1'
#380000
0'
#385000
b1 .
0$
b11 /
b100111 0
b100111 -
1'
#390000
0'
#395000
b1 .
1$
b1 /
1#
b101000 0
b101000 -
1'
#400000
0'
#405000
b1 .
0$
b10 /
b101001 0
b101001 -
1'
#410000
0'
#415000
b1 .
1$
b11 /
b101010 0
b101010 -
1'
#420000
0'
#425000
b1 .
0$
b1 /
0#
b101011 0
b101011 -
1'
#430000
0'
#435000
b1 .
1$
b10 /
b101100 0
b101100 -
1'
#440000
0'
#445000
b1 .
0$
b11 /
b101101 0
b101101 -
1'
#450000
0'
#455000
b1 .
1$
b1 /
1#
b101110 0
b101110 -
1'
#460000
0'
#465000
b1 .
0$
b10 /
b101111 0
b101111 -
1'
#470000
0'
#475000
b1 .
1$
b11 /
b110000 0
b110000 -
1'
#480000
0'
#485000
b1 .
0$
b1 /
0#
b110001 0
b110001 -
1'
#490000
0'
#495000
b1 .
1$
b10 /
b110010 0
b110010 -
1'
#500000
0'
#505000
b1 .
0$
b11 /
b110011 0
b110011 -
1'
#510000
0'
#515000
b1 .
1$
b1 /
1#
b110100 0
b110100 -
1'
#520000
0'
#525000
b1 .
0$
b10 /
b110101 0
b110101 -
1'
#530000
0'
#535000
b1 .
1$
b11 /
b110110 0
b110110 -
1'
#540000
0'
#545000
b1 .
0$
b1 /
0#
b110111 0
b110111 -
1'
#550000
0'
#555000
b1 .
1$
b10 /
b111000 0
b111000 -
1'
#560000
0'
#565000
b1 .
0$
b11 /
b111001 0
b111001 -
1'
#570000
0'
#575000
b1 .
1$
b1 /
1#
b111010 0
b111010 -
1'
#580000
0'
#585000
b1 .
0$
b10 /
b111011 0
b111011 -
1'
#590000
0'
#595000
b1 .
1$
b11 /
b111100 0
b111100 -
1'
#600000
0'
#605000
b1 .
0$
b1 /
0#
b111101 0
b111101 -
1'
#610000
0'
#615000
b1 .
1$
b10 /
b111110 0
b111110 -
1'
#620000
0'
#625000
b1 .
0$
b11 /
b111111 0
b111111 -
1'
#630000
0'
#635000
b1 .
1$
b1 /
1#
b1000000 0
b1000000 -
1'
#640000
0'
#645000
b1 .
0$
b10 /
b1000001 0
b1000001 -
1'
#650000
0'
#655000
b1 .
1$
b11 /
b1000010 0
b1000010 -
1'
#660000
0'
#665000
b1 .
0$
b1 /
0#
b1000011 0
b1000011 -
1'
#670000
0'
#675000
b1 .
1$
b10 /
b1000100 0
b1000100 -
1'
#680000
0'
#685000
b1 .
0$
b11 /
b1000101 0
b1000101 -
1'
#690000
0'
#695000
b1 .
1$
b1 /
1#
b1000110 0
b1000110 -
1'
#700000
0'
#705000
b1 .
0$
b10 /
b1000111 0
b1000111 -
1'
#710000
0'
#715000
b1 .
1$
b11 /
b1001000 0
b1001000 -
1'
#720000
0'
#725000
b1 .
0$
b1 /
0#
b1001001 0
b1001001 -
1'
#730000
0'
#735000
b1 .
1$
b10 /
b1001010 0
b1001010 -
1'
#740000
0'
#745000
b1 .
0$
b11 /
b1001011 0
b1001011 -
1'
#750000
0'
#755000
b1 .
1$
b1 /
1#
b1001100 0
b1001100 -
1'
#760000
0'
#765000
b1 .
0$
b10 /
b1001101 0
b1001101 -
1'
#770000
0'
#775000
b1 .
1$
b11 /
b1001110 0
b1001110 -
1'
#780000
0'
#785000
b1 .
0$
b1 /
0#
b1001111 0
b1001111 -
1'
#790000
0'
#795000
b1 .
1$
b10 /
b1010000 0
b1010000 -
1'
#800000
0'
#805000
b1 .
0$
b11 /
b1010001 0
b1010001 -
1'
#810000
0'
#815000
b1 .
1$
b1 /
1#
b1010010 0
b1010010 -
1'
#820000
0'
#825000
b1 .
0$
b10 /
b1010011 0
b1010011 -
1'
#830000
0'
#835000
b1 .
1$
b11 /
b1010100 0
b1010100 -
1'
#840000
0'
#845000
b1 .
0$
b1 /
0#
b1010101 0
b1010101 -
1'
#850000
0'
#855000
b1 .
1$
b10 /
b1010110 0
b1010110 -
1'
#860000
0'
#865000
b1 .
0$
b11 /
b1010111 0
b1010111 -
1'
#870000
0'
#875000
b1 .
1$
b1 /
1#
b1011000 0
b1011000 -
1'
#880000
0'
#885000
b1 .
0$
b10 /
b1011001 0
b1011001 -
1'
#890000
0'
#895000
b1 .
1$
b11 /
b1011010 0
b1011010 -
1'
#900000
0'
#905000
b1 .
0$
b1 /
0#
b1011011 0
b1011011 -
1'
#910000
0'
#915000
b1 .
1$
b10 /
b1011100 0
b1011100 -
1'
#920000
0'
#925000
b1 .
0$
b11 /
b1011101 0
b1011101 -
1'
#930000
0'
#935000
b1 .
1$
b1 /
1#
b1011110 0
b1011110 -
1'
#940000
0'
#945000
b1 .
0$
b10 /
b1011111 0
b1011111 -
1'
#950000
0'
#955000
b1 .
1$
b11 /
b1100000 0
b1100000 -
1'
#960000
0'
#965000
b1 .
0$
b1 /
0#
b1100001 0
b1100001 -
1'
#970000
0'
#975000
b1 .
1$
b10 /
b1100010 0
b1100010 -
1'
#980000
0'
#985000
b1 .
0$
b11 /
b1100011 0
b1100011 -
1'
#990000
0'
#995000
b1 .
1$
b1 /
1#
b1100100 0
b1100100 -
1'
#1000000
0'
#1005000
b1 .
0$
b10 /
b1100101 0
b1100101 -
1'
#1010000
0'
#1015000
b1 .
1$
b11 /
b1100110 0
b1100110 -
1'
#1020000
0'
#1025000
b1 .
0$
b1 /
0#
b1100111 0
b1100111 -
1'
#1030000
0'
#1035000
b1 .
1$
b10 /
b1101000 0
b1101000 -
1'
#1040000
0'
#1045000
b1 .
0$
b11 /
b1101001 0
b1101001 -
1'
#1050000
0'
#1055000
b1 .
1$
b1 /
1#
b1101010 0
b1101010 -
1'
#1060000
0'
#1065000
b1 .
0$
b10 /
b1101011 0
b1101011 -
1'
#1070000
0'
#1075000
b1 .
1$
b11 /
b1101100 0
b1101100 -
1'
#1080000
0'
#1085000
b1 .
0$
b1 /
0#
b1101101 0
b1101101 -
1'
#1090000
0'
#1095000
b1 .
1$
b10 /
b1101110 0
b1101110 -
1'
#1100000
0'
#1105000
b1 .
0$
b11 /
b1101111 0
b1101111 -
1'
#1110000
0'
#1115000
b1 .
1$
b1 /
1#
b1110000 0
b1110000 -
1'
#1120000
0'
#1125000
b1 .
0$
b10 /
b1110001 0
b1110001 -
1'
#1130000
0'
#1135000
b1 .
1$
b11 /
b1110010 0
b1110010 -
1'
#1140000
0'
#1145000
b1 .
0$
b1 /
0#
b1110011 0
b1110011 -
1'
#1150000
0'
#1155000
b1 .
1$
b10 /
b1110100 0
b1110100 -
1'
#1160000
0'
#1165000
b1 .
0$
b11 /
b1110101 0
b1110101 -
1'
#1170000
0'
#1175000
b1 .
1$
b1 /
1#
b1110110 0
b1110110 -
1'
#1180000
0'
#1185000
b1 .
0$
b10 /
b1110111 0
b1110111 -
1'
#1190000
0'
#1195000
b1 .
1$
b11 /
b1111000 0
b1111000 -
1'
#1200000
0'
#1205000
b1 .
0$
b1 /
0#
b1111001 0
b1111001 -
1'
#1210000
0'
#1215000
b1 .
1$
b10 /
b1111010 0
b1111010 -
1'
#1220000
0'
#1225000
b1 .
0$
b11 /
b1111011 0
b1111011 -
1'
#1230000
0'
#1235000
b1 .
1$
b1 /
1#
b1111100 0
b1111100 -
1'
#1240000
0'
#1245000
b1 .
0$
b10 /
b1111101 0
b1111101 -
1'
#1250000
0'
#1255000
b1 .
1$
b11 /
b1111110 0
b1111110 -
1'
#1260000
0'
#1265000
b1 .
0$
b1 /
0#
b1111111 0
b1111111 -
1'
#1270000
0'
#1275000
b1 .
1$
b10 /
b10000000 0
b10000000 -
1'
#1280000
0'
#1285000
b1 .
0$
b11 /
b10000001 0
b10000001 -
1'
#1290000
0'
#1295000
b1 .
1$
b1 /
1#
b10000010 0
b10000010 -
1'
#1300000
0'
#1305000
b1 .
0$
b10 /
b10000011 0
b10000011 -
1'
#1310000
0'
#1315000
b1 .
1$
b11 /
b10000100 0
b10000100 -
1'
#1320000
0'
#1325000
b1 .
0$
b1 /
0#
b10000101 0
b10000101 -
1'
#1330000
0'
#1335000
b1 .
1$
b10 /
b10000110 0
b10000110 -
1'
#1340000
0'
#1345000
b1 .
0$
b11 /
b10000111 0
b10000111 -
1'
#1350000
0'
#1355000
b1 .
1$
b1 /
1#
b10001000 0
b10001000 -
1'
#1360000
0'
#1365000
b1 .
0$
b10 /
b10001001 0
b10001001 -
1'
#1370000
0'
#1375000
b1 .
1$
b11 /
b10001010 0
b10001010 -
1'
#1380000
0'
#1385000
b1 .
0$
b1 /
0#
b10001011 0
b10001011 -
1'
#1390000
0'
#1395000
b1 .
1$
b10 /
b10001100 0
b10001100 -
1'
#1400000
0'
#1405000
b1 .
0$
b11 /
b10001101 0
b10001101 -
1'
#1410000
0'
#1415000
b1 .
1$
b1 /
1#
b10001110 0
b10001110 -
1'
#1420000
0'
#1425000
b1 .
0$
b10 /
b10001111 0
b10001111 -
1'
#1430000
0'
#1435000
b1 .
1$
b11 /
b10010000 0
b10010000 -
1'
#1440000
0'
#1445000
b1 .
0$
b1 /
0#
b10010001 0
b10010001 -
1'
#1450000
0'
#1455000
b1 .
1$
b10 /
b10010010 0
b10010010 -
1'
#1460000
0'
#1465000
b1 .
0$
b11 /
b10010011 0
b10010011 -
1'
#1470000
0'
#1475000
b1 .
1$
b1 /
1#
b10010100 0
b10010100 -
1'
#1480000
0'
#1485000
b1 .
0$
b10 /
b10010101 0
b10010101 -
1'
#1490000
0'
#1495000
b1 .
1$
b11 /
b10010110 0
b10010110 -
1'
#1500000
0'
#1505000
b1 .
0$
b1 /
0#
b10010111 0
b10010111 -
1'
#1510000
0'
#1515000
b1 .
1$
b10 /
b10011000 0
b10011000 -
1'
#1520000
0'
#1525000
b1 .
0$
b11 /
b10011001 0
b10011001 -
1'
#1530000
0'
#1535000
b1 .
1$
b1 /
1#
b10011010 0
b10011010 -
1'
#1540000
0'
#1545000
b1 .
0$
b10 /
b10011011 0
b10011011 -
1'
#1550000
0'
#1555000
b1 .
1$
b11 /
b10011100 0
b10011100 -
1'
#1560000
0'
#1565000
b1 .
0$
b1 /
0#
b10011101 0
b10011101 -
1'
#1570000
0'
#1575000
b1 .
1$
b10 /
b10011110 0
b10011110 -
1'
#1580000
0'
#1585000
b1 .
0$
b11 /
b10011111 0
b10011111 -
1'
#1590000
0'
#1595000
b1 .
1$
b1 /
1#
b10100000 0
b10100000 -
1'
#1600000
0'
#1605000
b1 .
0$
b10 /
b10100001 0
b10100001 -
1'
#1610000
0'
#1615000
b1 .
1$
b11 /
b10100010 0
b10100010 -
1'
#1620000
0'
#1625000
b1 .
0$
b1 /
0#
b10100011 0
b10100011 -
1'
#1630000
0'
#1635000
b1 .
1$
b10 /
b10100100 0
b10100100 -
1'
#1640000
0'
#1645000
b1 .
0$
b11 /
b10100101 0
b10100101 -
1'
#1650000
0'
#1655000
b1 .
1$
b1 /
1#
b10100110 0
b10100110 -
1'
#1660000
0'
#1665000
b1 .
0$
b10 /
b10100111 0
b10100111 -
1'
#1670000
0'
#1675000
b1 .
1$
b11 /
b10101000 0
b10101000 -
1'
#1680000
0'
#1685000
b1 .
0$
b1 /
0#
b10101001 0
b10101001 -
1'
#1690000
0'
#1695000
b1 .
1$
b10 /
b10101010 0
b10101010 -
1'
#1700000
0'
#1705000
b1 .
0$
b11 /
b10101011 0
b10101011 -
1'
#1710000
0'
#1715000
b1 .
1$
b1 /
1#
b10101100 0
b10101100 -
1'
#1720000
0'
#1725000
b1 .
0$
b10 /
b10101101 0
b10101101 -
1'
#1730000
0'
#1735000
b1 .
1$
b11 /
b10101110 0
b10101110 -
1'
#1740000
0'
#1745000
b1 .
0$
b1 /
0#
b10101111 0
b10101111 -
1'
#1750000
0'
#1755000
b1 .
1$
b10 /
b10110000 0
b10110000 -
1'
#1760000
0'
#1765000
b1 .
0$
b11 /
b10110001 0
b10110001 -
1'
#1770000
0'
#1775000
b1 .
1$
b1 /
1#
b10110010 0
b10110010 -
1'
#1780000
0'
#1785000
b1 .
0$
b10 /
b10110011 0
b10110011 -
1'
#1790000
0'
#1795000
b1 .
1$
b11 /
b10110100 0
b10110100 -
1'
#1800000
0'
#1805000
b1 .
0$
b1 /
0#
b10110101 0
b10110101 -
1'
#1810000
0'
#1815000
b1 .
1$
b10 /
b10110110 0
b10110110 -
1'
#1820000
0'
#1825000
b1 .
0$
b11 /
b10110111 0
b10110111 -
1'
#1830000
0'
#1835000
b1 .
1$
b1 /
1#
b10111000 0
b10111000 -
1'
#1840000
0'
#1845000
b1 .
0$
b10 /
b10111001 0
b10111001 -
1'
#1850000
0'
#1855000
b1 .
1$
b11 /
b10111010 0
b10111010 -
1'
#1860000
0'
#1865000
b1 .
0$
b1 /
0#
b10111011 0
b10111011 -
1'
#1870000
0'
#1875000
b1 .
1$
b10 /
b10111100 0
b10111100 -
1'
#1880000
0'
#1885000
b1 .
0$
b11 /
b10111101 0
b10111101 -
1'
#1890000
0'
#1895000
b1 .
1$
b1 /
1#
b10111110 0
b10111110 -
1'
#1900000
0'
#1905000
b1 .
0$
b10 /
b10111111 0
b10111111 -
1'
#1910000
0'
#1915000
b1 .
1$
b11 /
b11000000 0
b11000000 -
1'
#1920000
0'
#1925000
b1 .
0$
b1 /
0#
b11000001 0
b11000001 -
1'
#1930000
0'
#1935000
b1 .
1$
b10 /
b11000010 0
b11000010 -
1'
#1940000
0'
#1945000
b1 .
0$
b11 /
b11000011 0
b11000011 -
1'
#1950000
0'
#1955000
b1 .
1$
b1 /
1#
b11000100 0
b11000100 -
1'
#1960000
0'
#1965000
b1 .
0$
b10 /
b11000101 0
b11000101 -
1'
#1970000
0'
#1975000
b1 .
1$
b11 /
b11000110 0
b11000110 -
1'
#1980000
0'
#1985000
b1 .
0$
b1 /
0#
b11000111 0
b11000111 -
1'
#1990000
0'
#1995000
b1 .
1$
b10 /
b11001000 0
b11001000 -
1'
#2000000
0'
#2005000
b1 .
0$
b11 /
b11001001 0
b11001001 -
1'
#2010000
0'
#2015000
b1 .
1$
b1 /
1#
b11001010 0
b11001010 -
1'
#2020000
0'
#2025000
b1 .
0$
b10 /
b11001011 0
b11001011 -
1'
#2030000
0'
#2035000
b1 .
1$
b11 /
b11001100 0
b11001100 -
1'
#2040000
0'
#2045000
b1 .
0$
b1 /
0#
b11001101 0
b11001101 -
1'
#2050000
0'
#2055000
b1 .
1$
b10 /
b11001110 0
b11001110 -
1'
#2060000
0'
#2065000
b1 .
0$
b11 /
b11001111 0
b11001111 -
1'
#2070000
0'
#2075000
b1 .
1$
b1 /
1#
b11010000 0
b11010000 -
1'
#2080000
0'
#2085000
b1 .
0$
b10 /
b11010001 0
b11010001 -
1'
#2090000
0'
#2095000
b1 .
1$
b11 /
b11010010 0
b11010010 -
1'
#2100000
0'
#2105000
b1 .
0$
b1 /
0#
b11010011 0
b11010011 -
1'
#2110000
0'
#2115000
b1 .
1$
b10 /
b11010100 0
b11010100 -
1'
#2120000
0'
#2125000
b1 .
0$
b11 /
b11010101 0
b11010101 -
1'
#2130000
0'
#2135000
b1 .
1$
b1 /
1#
b11010110 0
b11010110 -
1'
#2140000
0'
#2145000
b1 .
0$
b10 /
b11010111 0
b11010111 -
1'
#2150000
0'
#2155000
b1 .
1$
b11 /
b11011000 0
b11011000 -
1'
#2160000
0'
#2165000
b1 .
0$
b1 /
0#
b11011001 0
b11011001 -
1'
#2170000
0'
#2175000
b1 .
1$
b10 /
b11011010 0
b11011010 -
1'
#2180000
0'
#2185000
b1 .
0$
b11 /
b11011011 0
b11011011 -
1'
#2190000
0'
#2195000
b1 .
1$
b1 /
1#
b11011100 0
b11011100 -
1'
#2200000
0'
#2205000
b1 .
0$
b10 /
b11011101 0
b11011101 -
1'
#2210000
0'
#2215000
b1 .
1$
b11 /
b11011110 0
b11011110 -
1'
#2220000
0'
#2225000
b1 .
0$
b1 /
0#
b11011111 0
b11011111 -
1'
#2230000
0'
#2235000
b1 .
1$
b10 /
b11100000 0
b11100000 -
1'
#2240000
0'
#2245000
b1 .
0$
b11 /
b11100001 0
b11100001 -
1'
#2250000
0'
#2255000
b1 .
1$
b1 /
1#
b11100010 0
b11100010 -
1'
#2260000
0'
#2265000
b1 .
0$
b10 /
b11100011 0
b11100011 -
1'
#2270000
0'
#2275000
b1 .
1$
b11 /
b11100100 0
b11100100 -
1'
#2280000
0'
#2285000
b1 .
0$
b1 /
0#
b11100101 0
b11100101 -
1'
#2290000
0'
#2295000
b1 .
1$
b10 /
b11100110 0
b11100110 -
1'
#2300000
0'
#2305000
b1 .
0$
b11 /
b11100111 0
b11100111 -
1'
#2310000
0'
#2315000
b1 .
1$
b1 /
1#
b11101000 0
b11101000 -
1'
#2320000
0'
#2325000
b1 .
0$
b10 /
b11101001 0
b11101001 -
1'
#2330000
0'
#2335000
b1 .
1$
b11 /
b11101010 0
b11101010 -
1'
#2340000
0'
#2345000
b1 .
0$
b1 /
0#
b11101011 0
b11101011 -
1'
#2350000
0'
#2355000
b1 .
1$
b10 /
b11101100 0
b11101100 -
1'
#2360000
0'
#2365000
b1 .
0$
b11 /
b11101101 0
b11101101 -
1'
#2370000
0'
#2375000
b1 .
1$
b1 /
1#
b11101110 0
b11101110 -
1'
#2380000
0'
#2385000
b1 .
0$
b10 /
b11101111 0
b11101111 -
1'
#2390000
0'
#2395000
b1 .
1$
b11 /
b11110000 0
b11110000 -
1'
#2400000
0'
#2405000
b1 .
0$
b1 /
0#
b11110001 0
b11110001 -
1'
#2410000
0'
#2415000
b1 .
1$
b10 /
b11110010 0
b11110010 -
1'
#2420000
0'
#2425000
b1 .
0$
b11 /
b11110011 0
b11110011 -
1'
#2430000
0'
#2435000
b1 .
1$
b1 /
1#
b11110100 0
b11110100 -
1'
#2440000
0'
#2445000
b1 .
0$
b10 /
b11110101 0
b11110101 -
1'
#2450000
0'
#2455000
b1 .
1$
b11 /
b11110110 0
b11110110 -
1'
#2460000
0'
#2465000
b1 .
0$
b1 /
0#
b11110111 0
b11110111 -
1'
#2470000
0'
#2475000
b1 .
1$
b10 /
b11111000 0
b11111000 -
1'
#2480000
0'
#2485000
b1 .
0$
b11 /
b11111001 0
b11111001 -
1'
#2490000
0'
#2495000
b1 .
1$
b1 /
1#
b11111010 0
b11111010 -
1'
#2500000
0'
#2505000
b1 .
0$
b10 /
b11111011 0
b11111011 -
1'
#2510000
0'
#2515000
b1 .
1$
b11 /
b1 0
1"
b11111100 -
1'
#2520000
0'
#2525000
b1 .
0$
b1 /
0#
b10 0
b11111101 -
1'
#2530000
0'
#2535000
b1 .
1$
b10 /
b11 0
b11111110 -
1'
#2540000
0'
#2545000
b1 .
0$
b11 /
b100 0
b11111111 -
1'
#2550000
0'
#2555000
b1 .
1$
b1 /
1#
b101 0
b100000000 -
1'
#2560000
0'
#2565000
b1 .
0$
b10 /
b110 0
b100000001 -
1'
#2570000
0'
#2575000
b1 .
1$
b11 /
b111 0
b100000010 -
1'
#2580000
0'
#2585000
b1 .
0$
b1 /
0#
b1000 0
b100000011 -
1'
#2590000
0'
#2595000
b1 .
1$
b10 /
b1001 0
b100000100 -
1'
#2600000
0'
#2605000
b1 .
0$
b11 /
b1010 0
b100000101 -
1'
#2610000
0'
#2615000
b1 .
1$
b1 /
1#
b1011 0
b100000110 -
1'
#2620000
0'
#2625000
b1 .
0$
b10 /
b1100 0
b100000111 -
1'
#2630000
0'
#2635000
b1 .
1$
b11 /
b1101 0
b100001000 -
1'
#2640000
0'
#2645000
b1 .
0$
b1 /
0#
b1110 0
b100001001 -
1'
#2650000
0'
#2655000
b1 .
1$
b10 /
b1111 0
b100001010 -
1'
#2660000
0'
#2665000
b1 .
0$
b11 /
b10000 0
b100001011 -
1'
#2670000
0'
#2675000
b1 .
1$
b1 /
1#
b10001 0
b100001100 -
1'
#2680000
0'
#2685000
b1 .
0$
b10 /
b10010 0
b100001101 -
1'
#2690000
0'
#2695000
b1 .
1$
b11 /
b10011 0
b100001110 -
1'
#2700000
0'
#2705000
b1 .
0$
b1 /
0#
b10100 0
b100001111 -
1'
#2710000
0'
#2715000
b1 .
1$
b10 /
b10101 0
b100010000 -
1'
#2720000
0'
#2725000
b1 .
0$
b11 /
b10110 0
b100010001 -
1'
#2730000
0'
#2735000
b1 .
1$
b1 /
1#
b10111 0
b100010010 -
1'
#2740000
0'
#2745000
b1 .
0$
b10 /
b11000 0
b100010011 -
1'
#2750000
0'
#2755000
b1 .
1$
b11 /
b11001 0
b100010100 -
1'
#2760000
0'
#2765000
b1 .
0$
b1 /
0#
b11010 0
b100010101 -
1'
#2770000
0'
#2775000
b1 .
1$
b10 /
b11011 0
b100010110 -
1'
#2780000
0'
#2785000
b1 .
0$
b11 /
b11100 0
b100010111 -
1'
#2790000
0'
#2795000
b1 .
1$
b1 /
1#
b11101 0
b100011000 -
1'
#2800000
0'
#2805000
b1 .
0$
b10 /
b11110 0
b100011001 -
1'
#2810000
0'
#2815000
b1 .
1$
b11 /
b11111 0
b100011010 -
1'
#2820000
0'
#2825000
b1 .
0$
b1 /
0#
b100000 0
b100011011 -
1'
#2830000
0'
#2835000
b1 .
1$
b10 /
b100001 0
b100011100 -
1'
#2840000
0'
#2845000
b1 .
0$
b11 /
b100010 0
b100011101 -
1'
#2850000
0'
#2855000
b1 .
1$
b1 /
1#
b100011 0
b100011110 -
1'
#2860000
0'
#2865000
b1 .
0$
b10 /
b100100 0
b100011111 -
1'
#2870000
0'
#2875000
b1 .
1$
b11 /
b100101 0
b100100000 -
1'
#2880000
0'
#2885000
b1 .
0$
b1 /
0#
b100110 0
b100100001 -
1'
#2890000
0'
#2895000
b1 .
1$
b10 /
b100111 0
b100100010 -
1'
#2900000
0'
#2905000
b1 .
0$
b11 /
b101000 0
b100100011 -
1'
#2910000
0'
#2915000
b1 .
1$
b1 /
1#
b101001 0
b100100100 -
1'
#2920000
0'
#2925000
b1 .
0$
b10 /
b101010 0
b100100101 -
1'
#2930000
0'
#2935000
b1 .
1$
b11 /
b101011 0
b100100110 -
1'
#2940000
0'
#2945000
b1 .
0$
b1 /
0#
b101100 0
b100100111 -
1'
#2950000
0'
#2955000
b1 .
1$
b10 /
b101101 0
b100101000 -
1'
#2960000
0'
#2965000
b1 .
0$
b11 /
b101110 0
b100101001 -
1'
#2970000
0'
#2975000
b1 .
1$
b1 /
1#
b101111 0
b100101010 -
1'
#2980000
0'
