control_fsm.v
`timescale 1ns / 100ps

// clock frequency : 1 KHz
// RESET siganl is active high

module control_fsm (entry_sensor, exit_sensor, vacant_parking,
				CLK , RESET,
				capacity, best_location, parkings, door_open_signal, full_signal);
    
    input entry_sensor, exit_sensor, CLK, RESET;
	input [1:0] vacant_parking;
	output reg door_open_signal, full_signal;
	output reg [2:0] capacity;
	output [1:0] best_location;
	output reg [3:0] parkings;

    // with 1KHz clock frequency we can count at most 63s 
	reg [15:0] timer;

    reg [2:0] state;
    parameter IDLE = 3'b000 , DOOR_OPEN = 3'b001 , FULL = 3'b010 , CAR_ENTERING = 3'b011 , CAR_EXITING = 3'b100;

    wire full, empty;
    
    // 0 -> exiting
    // 1 -> entering
    reg temp_state;

    assign full = parkings[0] & parkings[1] & parkings[2] & parkings[3];
	assign empty = ~(parkings[0] | parkings[1] | parkings[2] | parkings[3]);

    // The case in which parkings is equal to 1111 is considered as don't care
    assign best_location[1] = parkings[0] & parkings[1];
    assign best_location[0] = (((~parkings[1]) & parkings[0]) |
                                (parkings[2] & parkings[0]));
   		                      
    always @ (posedge CLK or posedge RESET) begin
        if (RESET) begin
            state = IDLE; // Initialize to IDLE
            parkings = 4'b0000;
            capacity = 3'b100;
            door_open_signal = 1'b0;
            full_signal = 1'b0;
        end 
        else begin
            // timer <= timer;  // Default assignments to prevent latches
            // state <= state;  // Default assignments to prevent latches
            case (state)
                IDLE : begin
                    timer <= 16'b0000000000000000;
                    if (entry_sensor & ~exit_sensor)
                        if (full) begin
                            state = FULL;
    						full_signal = 1'b1;
    					end
                        else begin
                            state = DOOR_OPEN;
                            temp_state = 1'b1; // Entering
	    					door_open_signal = 1'b1;
                        end
                    if (~entry_sensor & exit_sensor)
                        if (~empty) begin
                            state = DOOR_OPEN;
                            temp_state = 1'b0; // Exiting
						    door_open_signal = 1'b1;
                        end
                end

                DOOR_OPEN : begin
			    	timer = timer + 1;
				    if (timer > 10 /*FOR TEST*/ /*IT MUST BE 10000*/) begin
					    if (temp_state)
                            state = CAR_ENTERING;
                        else
                            state = CAR_EXITING;
    					door_open_signal = 1'b0;
	    			end
		    	 end

                FULL : begin 
				    timer = timer + 1;
    				if (timer > 3 /*FOR TEST*/ /*IT MUST BE 3000*/) begin
	    				state = IDLE;
		    			full_signal = 1'b0;
			    	end
			    end

                CAR_ENTERING : begin 
		    		parkings[3] = parkings[3] |  (parkings[0] & parkings[1] & parkings[2]);
			    	parkings[2] = parkings[2] | (parkings[0] & parkings[1]);
				    parkings[1] = parkings[1] | parkings[0];
					parkings[0] = 1'b1;

                    capacity = capacity - 1;

                    state = IDLE;
				end

                CAR_EXITING: begin
	    			parkings[3] = parkings[3] & (~vacant_parking[0] | ~vacant_parking[1]);
		    		parkings[2] = parkings[2] & (~vacant_parking[0] | vacant_parking[1]);
			    	parkings[1] = parkings[1] & (vacant_parking[0] | ~vacant_parking[1]);
				    parkings[0] = parkings[0] & (vacant_parking[0] | vacant_parking[1]);

                    capacity = capacity + 1;

                    state = IDLE;
				end
            endcase
        end
    end                            

endmodule

control_fsm_test.v
`include "control_fsm.v"
`timescale 1us / 100ns

module control_fsm_test();

    wire door_open_signal, full_signal;
	wire [2:0] capacity;
	wire [1:0] best_location;
	wire [3:0] parkings;

    reg entry_sensor, exit_sensor, CLK, RESET;
	reg [1:0] vacant_parking;

    control_fsm fsm (entry_sensor, exit_sensor, vacant_parking,
				CLK , RESET,
				capacity, best_location, parkings, door_open_signal, full_signal);

    initial begin
        CLK = 1'b1;
        repeat (100) // 50 milisecond. 
            #500 CLK = ~CLK;
    end

    initial begin
        $dumpfile("control_fsm_test.vcd");
        $dumpvars(0, control_fsm_test);

        RESET = 1'b1; #10
        RESET = 1'b0; #10

        entry_sensor = 1'b1;
        exit_sensor = 1'b0; #1500;

        entry_sensor = 1'b0;
        exit_sensor = 1'b0;


        

    end

endmodule

control_fsm_test.vcd
$date
	Sat Dec 14 23:27:17 2024
$end
$version
	Icarus Verilog
$end
$timescale
	100ps
$end
$scope module control_fsm_test $end
$var wire 4 ! parkings [3:0] $end
$var wire 1 " full_signal $end
$var wire 1 # door_open_signal $end
$var wire 3 $ capacity [2:0] $end
$var wire 2 % best_location [1:0] $end
$var reg 1 & CLK $end
$var reg 1 ' RESET $end
$var reg 1 ( entry_sensor $end
$var reg 1 ) exit_sensor $end
$var reg 2 * vacant_parking [1:0] $end
$scope module fsm $end
$var wire 1 & CLK $end
$var wire 1 ' RESET $end
$var wire 1 + empty $end
$var wire 1 ( entry_sensor $end
$var wire 1 ) exit_sensor $end
$var wire 1 , full $end
$var wire 2 - vacant_parking [1:0] $end
$var wire 2 . best_location [1:0] $end
$var parameter 3 / CAR_ENTERING $end
$var parameter 3 0 CAR_EXITING $end
$var parameter 3 1 DOOR_OPEN $end
$var parameter 3 2 FULL $end
$var parameter 3 3 IDLE $end
$var reg 3 4 capacity [2:0] $end
$var reg 1 # door_open_signal $end
$var reg 1 " full_signal $end
$var reg 4 5 parkings [3:0] $end
$var reg 3 6 state [2:0] $end
$var reg 1 7 temp_state $end
$var reg 16 8 timer [15:0] $end
$upscope $end
$upscope $end
$enddefinitions $end
$comment Show the parameter values. $end
$dumpall
b0 3
b10 2
b1 1
b100 0
b11 /
$end
#0
$dumpvars
bx 8
x7
b0 6
b0 5
b100 4
b0 .
bx -
0,
1+
bx *
x)
x(
1'
1&
b0 %
b100 $
0#
0"
b0 !
$end
#100000
0'
#200000
0)
1(
#5000000
0&
#10000000
b0 8
1#
17
b1 6
1&
#15000000
0&
#15200000
0(
#20000000
b1 8
1&
#25000000
0&
#30000000
b10 8
1&
#35000000
0&
#40000000
b11 8
1&
#45000000
0&
#50000000
b100 8
1&
#55000000
0&
#60000000
b101 8
1&
#65000000
0&
#70000000
b110 8
1&
#75000000
0&
#80000000
b111 8
1&
#85000000
0&
#90000000
b1000 8
1&
#95000000
0&
#100000000
b1001 8
1&
#105000000
0&
#110000000
b1010 8
1&
#115000000
0&
#120000000
0#
b11 6
b1011 8
1&
#125000000
0&
#130000000
0+
b1 %
b1 .
b0 6
b11 $
b11 4
b1 !
b1 5
1&
#135000000
0&
#135200000
1(
#140000000
b0 8
1#
b1 6
1&
#145000000
0&
#150000000
b1 8
1&
#150200000
0(
#155000000
0&
#160000000
b10 8
1&
#165000000
0&
#170000000
b11 8
1&
#175000000
0&
#180000000
b100 8
1&
#185000000
0&
#190000000
b101 8
1&
#195000000
0&
#200000000
b110 8
1&
#205000000
0&
#210000000
b111 8
1&
#215000000
0&
#220000000
b1000 8
1&
#225000000
0&
#230000000
b1001 8
1&
#235000000
0&
#240000000
b1010 8
1&
#245000000
0&
#250000000
0#
b11 6
b1011 8
1&
#255000000
0&
#260000000
b10 %
b10 .
b0 6
b10 $
b10 4
b11 !
b11 5
1&
#265000000
0&
#270000000
b0 8
1&
#270200000
1(
#275000000
0&
#280000000
1#
b1 6
1&
#285000000
0&
#285200000
0(
#290000000
b1 8
1&
#295000000
0&
#300000000
b10 8
1&
#305000000
0&
#310000000
b11 8
1&
#315000000
0&
#320000000
b100 8
1&
#325000000
0&
#330000000
b101 8
1&
#335000000
0&
#340000000
b110 8
1&
#345000000
0&
#350000000
b111 8
1&
#355000000
0&
#360000000
b1000 8
1&
#365000000
0&
#370000000
b1001 8
1&
#375000000
0&
#380000000
b1010 8
1&
#385000000
0&
#390000000
0#
b11 6
b1011 8
1&
#395000000
0&
#400000000
b11 %
b11 .
b0 6
b1 $
b1 4
b111 !
b111 5
1&
#405000000
0&
#405200000
1(
#410000000
b0 8
1#
b1 6
1&
#415000000
0&
#420000000
b1 8
1&
#420200000
0(
#425000000
0&
#430000000
b10 8
1&
#435000000
0&
#440000000
b11 8
1&
#445000000
0&
#450000000
b100 8
1&
#455000000
0&
#460000000
b101 8
1&
#465000000
0&
#470000000
b110 8
1&
#475000000
0&
#480000000
b111 8
1&
#485000000
0&
#490000000
b1000 8
1&
#495000000
0&
#500000000
b1001 8
1&
#505000000
0&
#510000000
b1010 8
1&
#515000000
0&
#520000000
0#
b11 6
b1011 8
1&
#525000000
0&
#530000000
1,
b0 6
b0 $
b0 4
b1111 !
b1111 5
1&
#535000000
0&
#540000000
b0 8
1&
#540200000
1(
#545000000
0&
#550000000
1"
b10 6
1&
#555000000
0&
#555200000
0(
#560000000
b1 8
1&
#565000000
0&
#570000000
b10 8
1&
#575000000
0&
#580000000
b11 8
1&
#585000000
0&
#590000000
0"
b0 6
b100 8
1&
#595000000
0&
#600000000
b0 8
1&
#605000000
0&
#610000000
1&
#615000000
0&
#620000000
1&
#625000000
0&
#630000000
1&
#635000000
0&
#640000000
1&
#645000000
0&
#650000000
1&
#655000000
0&
#660000000
1&
#665000000
0&
#670000000
1&
#675000000
0&
#675200000
b10 *
b10 -
1)
#680000000
1#
07
b1 6
1&
#685000000
0&
#690000000
b1 8
1&
#690200000
0)
#695000000
0&
#700000000
b10 8
1&
#705000000
0&
#710000000
b11 8
1&
#715000000
0&
#720000000
b100 8
1&
#725000000
0&
#730000000
b101 8
1&
#735000000
0&
#740000000
b110 8
1&
#745000000
0&
#750000000
b111 8
1&
#755000000
0&
#760000000
b1000 8
1&
#765000000
0&
#770000000
b1001 8
1&
#775000000
0&
#780000000
b1010 8
1&
#785000000
0&
#790000000
0#
b100 6
b1011 8
1&
#795000000
0&
#800000000
0,
b1 %
b1 .
b0 6
b1 $
b1 4
b1101 !
b1101 5
1&
#805000000
0&
#810000000
b0 8
1&
#810200000
b0 *
b0 -
1)
#815000000
0&
#820000000
1#
b1 6
1&
#825000000
0&
#825200000
0)
#830000000
b1 8
1&
#835000000
0&
#840000000
b10 8
1&
#845000000
0&
#850000000
b11 8
1&
#855000000
0&
#860000000
b100 8
1&
#865000000
0&
#870000000
b101 8
1&
#875000000
0&
#880000000
b110 8
1&
#885000000
0&
#890000000
b111 8
1&
#895000000
0&
#900000000
b1000 8
1&
#905000000
0&
#910000000
b1001 8
1&
#915000000
0&
#920000000
b1010 8
1&
#925000000
0&
#930000000
0#
b100 6
b1011 8
1&
#935000000
0&
#940000000
b0 %
b0 .
b0 6
b10 $
b10 4
b1100 !
b1100 5
1&
#945000000
0&
#945200000
1(
#950000000
b0 8
1#
17
b1 6
1&
#955000000
0&
#960000000
b1 8
1&
#960200000
0(
#965000000
0&
#970000000
b10 8
1&
#975000000
0&
#980000000
b11 8
1&
#985000000
0&
#990000000
b100 8
1&
#995000000
0&
#1000000000
b101 8
1&
#1005000000
0&
#1010000000
b110 8
1&
#1015000000
0&
#1020000000
b111 8
1&
#1025000000
0&
#1030000000
b1000 8
1&
#1035000000
0&
#1040000000
b1001 8
1&
#1045000000
0&
#1050000000
b1010 8
1&
#1055000000
0&
#1060000000
0#
b11 6
b1011 8
1&
#1065000000
0&
#1070000000
b1 %
b1 .
b0 6
b1 $
b1 4
b1101 !
b1101 5
1&
#1075000000
0&
#1080000000
b0 8
1&
