control_fsm.v
`timescale 1ns / 100ps

// clock frequency : 1 KHz
// RESET siganl is active high

module control_fsm (entry_sensor, exit_sensor, vacant_parking,
				CLK , RESET,
				capacity, best_location, parkings, door_open_signal, full_signal);
    
    input entry_sensor, exit_sensor, CLK, RESET;
	input [1:0] vacant_parking;
	output reg door_open_signal, full_signal;
	output reg [2:0] capacity;
	output [1:0] best_location;
	output reg [3:0] parkings;

    // with 1KHz clock frequency we can count at most 63s 
	reg [15:0] timer;

    reg [2:0] state;
    parameter IDLE = 3'b000 , DOOR_OPEN = 3'b001 , FULL = 3'b010 , CAR_ENTERING = 3'b011 , CAR_EXITING = 3'b100;

    wire full, empty;
    
    // 0 -> exiting
    // 1 -> entering
    reg temp_state;

    assign full = parkings[0] & parkings[1] & parkings[2] & parkings[3];
	assign empty = ~(parkings[0] | parkings[1] | parkings[2] | parkings[3]);

    // The case in which parkings is equal to 1111 is considered as don't care
    assign best_location[1] = parkings[0] & parkings[1];
    assign best_location[0] = (((~parkings[1]) & parkings[0]) |
                                (parkings[2] & parkings[0]));
   		                      
    always @ (posedge CLK or posedge RESET) begin
        if (RESET) begin
            state = IDLE; // Initialize to IDLE
            parkings = 4'b0000;
            capacity = 3'b100;
            door_open_signal = 1'b0;
            full_signal = 1'b0;
        end 
        else begin
            // timer <= timer;  // Default assignments to prevent latches
            // state <= state;  // Default assignments to prevent latches
            case (state)
                IDLE : begin
                    timer <= 16'b0000000000000000;
                    if (entry_sensor & ~exit_sensor)
                        if (full) begin
                            state = FULL;
    						full_signal = 1'b1;
    					end
                        else begin
                            state = DOOR_OPEN;
                            temp_state = 1'b1; // Entering
	    					door_open_signal = 1'b1;
                        end
                    if (~entry_sensor & exit_sensor)
                        if (~empty) begin
                            state = DOOR_OPEN;
                            temp_state = 1'b0; // Exiting
						    door_open_signal = 1'b1;
                        end
                end

                DOOR_OPEN : begin
			    	timer = timer + 1;
				    if (timer > 10 /*IT MUST BE 10000*/) begin
					    if (temp_state)
                            state = CAR_ENTERING;
                        else
                            state = CAR_EXITING;
    					door_open_signal = 1'b0;
	    			end
		    	 end

                FULL : begin 
				    timer = timer + 1;
    				if (timer > 3 /*IT MUST BE 3000*/) begin
	    				state = IDLE;
		    			full_signal = 1'b0;
			    	end
			    end

                CAR_ENTERING : begin 
		    		parkings[3] = parkings[3] |  (parkings[0] & parkings[1] & parkings[2]);
			    	parkings[2] = parkings[2] | (parkings[0] & parkings[1]);
				    parkings[1] = parkings[1] | parkings[0];
					parkings[0] = 1'b1;

                    capacity = capacity - 1;

                    state = IDLE;
				end

                CAR_EXITING: begin
	    			parkings[3] = parkings[3] & (~vacant_parking[0] | ~vacant_parking[1]);
		    		parkings[2] = parkings[2] & (~vacant_parking[0] | vacant_parking[1]);
			    	parkings[1] = parkings[1] & (vacant_parking[0] | ~vacant_parking[1]);
				    parkings[0] = parkings[0] & (vacant_parking[0] | vacant_parking[1]);

                    capacity = capacity + 1;

                    state = IDLE;
				end
            endcase
        end
    end                            

endmodule

control_fsm_file_test.v
`include "control_fsm.v"
`timescale 1us / 100ns

module control_fsm_file_test();

    wire door_open_signal, full_signal;
	wire [2:0] capacity;
	wire [1:0] best_location;
	wire [3:0] parkings;

    reg entry_sensor, exit_sensor, CLK, RESET;
	reg [1:0] vacant_parking;

    control_fsm fsm (entry_sensor, exit_sensor, vacant_parking,
				CLK , RESET,
				capacity, best_location, parkings, door_open_signal, full_signal);

    initial begin
        CLK = 1'b1;
        repeat (1000) // 500 milisecond. 
            #500 CLK = ~CLK;
    end

    integer infile, outfile, scan_status;
    reg [3:0] inp;
    reg d , f;

    initial begin
        $dumpfile("control_fsm_file_test.vcd");
        $dumpvars(0, control_fsm_file_test);

        infile = $fopen("input.txt", "r");
        if (infile == 0) begin
            $display("Error: Could not open input file");
            $finish;
        end

        outfile = $fopen("output.txt", "w");
        if (outfile == 0) begin
            $display("Error : Could not open output file");
            $finish;
        end

        RESET = 1'b1; #10
        RESET = 1'b0; #10

        while (!$feof(infile)) begin
            scan_status = $fscanf(infile, "%b\n", inp);
            if (scan_status == 1) begin
                entry_sensor = inp[3];
                exit_sensor = inp[2];
                vacant_parking = {inp[0], inp[1]};
                #1000;
                if (entry_sensor)
                    entry_sensor = 1'b0;
                if (exit_sensor)
                    exit_sensor = 1'b0;
                if (full_signal)
                    f = 1'b1;
                if (door_open_signal) 
                    d = 1'b1;
                #12000;
                $fwrite(outfile, "%b [%d,%d] ", parkings, capacity, best_location);
                if (f) begin
                    $fwrite(outfile, " full");
                    f = 1'b0;
                end
                if (d) begin
                    $fwrite(outfile, " door");
                    d = 1'b0;
                end
                $fwrite (outfile, "\n"); 
            end else begin
                $display("Error : Failed to read data from file");
            end
        end

        $fclose(infile);
        $fclose(outfile);

        end

endmodule

control_fsm_file_test.vcd
$date
	Wed Dec 25 22:32:40 2024
$end
$version
	Icarus Verilog
$end
$timescale
	100ps
$end
$scope module control_fsm_file_test $end
$var wire 4 ! parkings [3:0] $end
$var wire 1 " full_signal $end
$var wire 1 # door_open_signal $end
$var wire 3 $ capacity [2:0] $end
$var wire 2 % best_location [1:0] $end
$var reg 1 & CLK $end
$var reg 1 ' RESET $end
$var reg 1 ( d $end
$var reg 1 ) entry_sensor $end
$var reg 1 * exit_sensor $end
$var reg 1 + f $end
$var reg 4 , inp [3:0] $end
$var reg 2 - vacant_parking [1:0] $end
$var integer 32 . infile [31:0] $end
$var integer 32 / outfile [31:0] $end
$var integer 32 0 scan_status [31:0] $end
$scope module fsm $end
$var wire 1 & CLK $end
$var wire 1 ' RESET $end
$var wire 1 1 empty $end
$var wire 1 ) entry_sensor $end
$var wire 1 * exit_sensor $end
$var wire 1 2 full $end
$var wire 2 3 vacant_parking [1:0] $end
$var wire 2 4 best_location [1:0] $end
$var parameter 3 5 CAR_ENTERING $end
$var parameter 3 6 CAR_EXITING $end
$var parameter 3 7 DOOR_OPEN $end
$var parameter 3 8 FULL $end
$var parameter 3 9 IDLE $end
$var reg 3 : capacity [2:0] $end
$var reg 1 # door_open_signal $end
$var reg 1 " full_signal $end
$var reg 4 ; parkings [3:0] $end
$var reg 3 < state [2:0] $end
$var reg 1 = temp_state $end
$var reg 16 > timer [15:0] $end
$upscope $end
$upscope $end
$enddefinitions $end
$comment Show the parameter values. $end
$dumpall
b0 9
b10 8
b1 7
b100 6
b11 5
$end
#0
$dumpvars
bx >
x=
b0 <
b0 ;
b100 :
b0 4
bx 3
02
11
bx 0
b10000000000000000000000000000100 /
b10000000000000000000000000000011 .
bx -
bx ,
x+
x*
x)
x(
1'
1&
b0 %
b100 $
0#
0"
b0 !
$end
#100000
0'
#200000
b0 -
b0 3
0*
0)
b1 0
b0 ,
#5000000
0&
#10000000
b0 >
1&
#15000000
0&
#20000000
1&
#25000000
0&
#30000000
1&
#35000000
0&
#40000000
1&
#45000000
0&
#50000000
1&
#55000000
0&
#60000000
1&
#65000000
0&
#70000000
1&
#75000000
0&
#80000000
1&
#85000000
0&
#90000000
1&
#95000000
0&
#100000000
1&
#105000000
0&
#110000000
1&
#115000000
0&
#120000000
1&
#125000000
0&
#130000000
1&
#130200000
1)
b1000 ,
#135000000
0&
#140000000
1#
1=
b1 <
1&
#140200000
1(
0)
#145000000
0&
#150000000
b1 >
1&
#155000000
0&
#160000000
b10 >
1&
#165000000
0&
#170000000
b11 >
1&
#175000000
0&
#180000000
b100 >
1&
#185000000
0&
#190000000
b101 >
1&
#195000000
0&
#200000000
b110 >
1&
#205000000
0&
#210000000
b111 >
1&
#215000000
0&
#220000000
b1000 >
1&
#225000000
0&
#230000000
b1001 >
1&
#235000000
0&
#240000000
b1010 >
1&
#245000000
0&
#250000000
0#
b11 <
b1011 >
1&
#255000000
0&
#260000000
01
b1 %
b1 4
b0 <
b11 $
b11 :
b1 !
b1 ;
1&
#260200000
b10 -
b10 3
1)
b1001 ,
0(
#265000000
0&
#270000000
b0 >
1#
b1 <
1&
#270200000
1(
0)
#275000000
0&
#280000000
b1 >
1&
#285000000
0&
#290000000
b10 >
1&
#295000000
0&
#300000000
b11 >
1&
#305000000
0&
#310000000
b100 >
1&
#315000000
0&
#320000000
b101 >
1&
#325000000
0&
#330000000
b110 >
1&
#335000000
0&
#340000000
b111 >
1&
#345000000
0&
#350000000
b1000 >
1&
#355000000
0&
#360000000
b1001 >
1&
#365000000
0&
#370000000
b1010 >
1&
#375000000
0&
#380000000
0#
b11 <
b1011 >
1&
#385000000
0&
#390000000
b10 %
b10 4
b0 <
b10 $
b10 :
b11 !
b11 ;
1&
#390200000
b1 ,
0(
#395000000
0&
#400000000
b0 >
1&
#405000000
0&
#410000000
1&
#415000000
0&
#420000000
1&
#425000000
0&
#430000000
1&
#435000000
0&
#440000000
1&
#445000000
0&
#450000000
1&
#455000000
0&
#460000000
1&
#465000000
0&
#470000000
1&
#475000000
0&
#480000000
1&
#485000000
0&
#490000000
1&
#495000000
0&
#500000000
1&
#505000000
0&
#510000000
1&
#515000000
0&
#520000000
1&
#520200000
b11 -
b11 3
1)
b1011 ,
#525000000
0&
#530000000
1#
b1 <
1&
#530200000
1(
0)
#535000000
0&
#540000000
b1 >
1&
#545000000
0&
#550000000
b10 >
1&
#555000000
0&
#560000000
b11 >
1&
#565000000
0&
#570000000
b100 >
1&
#575000000
0&
#580000000
b101 >
1&
#585000000
0&
#590000000
b110 >
1&
#595000000
0&
#600000000
b111 >
1&
#605000000
0&
#610000000
b1000 >
1&
#615000000
0&
#620000000
b1001 >
1&
#625000000
0&
#630000000
b1010 >
1&
#635000000
0&
#640000000
0#
b11 <
b1011 >
1&
#645000000
0&
#650000000
b11 %
b11 4
b0 <
b1 $
b1 :
b111 !
b111 ;
1&
#650200000
b10 -
b10 3
1*
b101 ,
0(
#655000000
0&
#660000000
b0 >
1#
0=
b1 <
1&
#660200000
1(
0*
#665000000
0&
#670000000
b1 >
1&
#675000000
0&
#680000000
b10 >
1&
#685000000
0&
#690000000
b11 >
1&
#695000000
0&
#700000000
b100 >
1&
#705000000
0&
#710000000
b101 >
1&
#715000000
0&
#720000000
b110 >
1&
#725000000
0&
#730000000
b111 >
1&
#735000000
0&
#740000000
b1000 >
1&
#745000000
0&
#750000000
b1001 >
1&
#755000000
0&
#760000000
b1010 >
1&
#765000000
0&
#770000000
0#
b100 <
b1011 >
1&
#775000000
0&
#780000000
b1 %
b1 4
b0 <
b101 !
b101 ;
b10 $
b10 :
1&
#780200000
b0 -
b0 3
1)
b1000 ,
0(
#785000000
0&
#790000000
b0 >
1#
1=
b1 <
1&
#790200000
1(
0)
#795000000
0&
#800000000
b1 >
1&
#805000000
0&
#810000000
b10 >
1&
#815000000
0&
#820000000
b11 >
1&
#825000000
0&
#830000000
b100 >
1&
#835000000
0&
#840000000
b101 >
1&
#845000000
0&
#850000000
b110 >
1&
#855000000
0&
#860000000
b111 >
1&
#865000000
0&
#870000000
b1000 >
1&
#875000000
0&
#880000000
b1001 >
1&
#885000000
0&
#890000000
b1010 >
1&
#895000000
0&
#900000000
0#
b11 <
b1011 >
1&
#905000000
0&
#910000000
b11 %
b11 4
b0 <
b1 $
b1 :
b111 !
b111 ;
1&
#910200000
1*
b100 ,
0(
#915000000
0&
#920000000
b0 >
1#
0=
b1 <
1&
#920200000
1(
0*
#925000000
0&
#930000000
b1 >
1&
#935000000
0&
#940000000
b10 >
1&
#945000000
0&
#950000000
b11 >
1&
#955000000
0&
#960000000
b100 >
1&
#965000000
0&
#970000000
b101 >
1&
#975000000
0&
#980000000
b110 >
1&
#985000000
0&
#990000000
b111 >
1&
#995000000
0&
#1000000000
b1000 >
1&
#1005000000
0&
#1010000000
b1001 >
1&
#1015000000
0&
#1020000000
b1010 >
1&
#1025000000
0&
#1030000000
0#
b100 <
b1011 >
1&
#1035000000
0&
#1040000000
b0 %
b0 4
b0 <
b110 !
b110 ;
b10 $
b10 :
1&
#1040200000
1*
0(
#1045000000
0&
#1050000000
b0 >
1&
#1050200000
0*
#1055000000
0&
#1060000000
1&
#1065000000
0&
#1070000000
1&
#1075000000
0&
#1080000000
1&
#1085000000
0&
#1090000000
1&
#1095000000
0&
#1100000000
1&
#1105000000
0&
#1110000000
1&
#1115000000
0&
#1120000000
1&
#1125000000
0&
#1130000000
1&
#1135000000
0&
#1140000000
1&
#1145000000
0&
#1150000000
1&
#1155000000
0&
#1160000000
1&
#1165000000
0&
#1170000000
1&
#1170200000
b10 -
b10 3
1)
b1001 ,
#1175000000
0&
#1180000000
1#
1=
b1 <
1&
#1180200000
1(
0)
#1185000000
0&
#1190000000
b1 >
1&
#1195000000
0&
#1200000000
b10 >
1&
#1205000000
0&
#1210000000
b11 >
1&
#1215000000
0&
#1220000000
b100 >
1&
#1225000000
0&
#1230000000
b101 >
1&
#1235000000
0&
#1240000000
b110 >
1&
#1245000000
0&
#1250000000
b111 >
1&
#1255000000
0&
#1260000000
b1000 >
1&
#1265000000
0&
#1270000000
b1001 >
1&
#1275000000
0&
#1280000000
b1010 >
1&
#1285000000
0&
#1290000000
0#
b11 <
b1011 >
1&
#1295000000
0&
#1300000000
b11 %
b11 4
b0 <
b1 $
b1 :
b111 !
b111 ;
1&
#1300200000
b0 -
b0 3
1)
b1000 ,
0(
#1305000000
0&
#1310000000
b0 >
1#
b1 <
1&
#1310200000
1(
0)
#1315000000
0&
#1320000000
b1 >
1&
#1325000000
0&
#1330000000
b10 >
1&
#1335000000
0&
#1340000000
b11 >
1&
#1345000000
0&
#1350000000
b100 >
1&
#1355000000
0&
#1360000000
b101 >
1&
#1365000000
0&
#1370000000
b110 >
1&
#1375000000
0&
#1380000000
b111 >
1&
#1385000000
0&
#1390000000
b1000 >
1&
#1395000000
0&
#1400000000
b1001 >
1&
#1405000000
0&
#1410000000
b1010 >
1&
#1415000000
0&
#1420000000
0#
b11 <
b1011 >
1&
#1425000000
0&
#1430000000
12
b0 <
b0 $
b0 :
b1111 !
b1111 ;
1&
#1430200000
b11 -
b11 3
1)
b1011 ,
0(
#1435000000
0&
#1440000000
b0 >
1"
b10 <
1&
#1440200000
1+
0)
#1445000000
0&
#1450000000
b1 >
1&
#1455000000
0&
#1460000000
b10 >
1&
#1465000000
0&
#1470000000
b11 >
1&
#1475000000
0&
#1480000000
0"
b0 <
b100 >
1&
#1485000000
0&
#1490000000
b0 >
1&
#1495000000
0&
#1500000000
1&
#1505000000
0&
#1510000000
1&
#1515000000
0&
#1520000000
1&
#1525000000
0&
#1530000000
1&
#1535000000
0&
#1540000000
1&
#1545000000
0&
#1550000000
1&
#1555000000
0&
#1560000000
1&
#1560200000
b0 -
b0 3
1)
b1000 ,
0+
#1565000000
0&
#1570000000
1"
b10 <
1&
#1570200000
1+
0)
#1575000000
0&
#1580000000
b1 >
1&
#1585000000
0&
#1590000000
b10 >
1&
#1595000000
0&
#1600000000
b11 >
1&
#1605000000
0&
#1610000000
0"
b0 <
b100 >
1&
#1615000000
0&
#1620000000
b0 >
1&
#1625000000
0&
#1630000000
1&
#1635000000
0&
#1640000000
1&
#1645000000
0&
#1650000000
1&
#1655000000
0&
#1660000000
1&
#1665000000
0&
#1670000000
1&
#1675000000
0&
#1680000000
1&
#1685000000
0&
#1690000000
1&
#1690200000
b0 ,
0+
#1695000000
0&
#1700000000
1&
#1705000000
0&
#1710000000
1&
#1715000000
0&
#1720000000
1&
#1725000000
0&
#1730000000
1&
#1735000000
0&
#1740000000
1&
#1745000000
0&
#1750000000
1&
#1755000000
0&
#1760000000
1&
#1765000000
0&
#1770000000
1&
#1775000000
0&
#1780000000
1&
#1785000000
0&
#1790000000
1&
#1795000000
0&
#1800000000
1&
#1805000000
0&
#1810000000
1&
#1815000000
0&
#1820000000
1&
#1820200000
1*
b100 ,
#1825000000
0&
#1830000000
1#
0=
b1 <
1&
#1830200000
1(
0*
#1835000000
0&
#1840000000
b1 >
1&
#1845000000
0&
#1850000000
b10 >
1&
#1855000000
0&
#1860000000
b11 >
1&
#1865000000
0&
#1870000000
b100 >
1&
#1875000000
0&
#1880000000
b101 >
1&
#1885000000
0&
#1890000000
b110 >
1&
#1895000000
0&
#1900000000
b111 >
1&
#1905000000
0&
#1910000000
b1000 >
1&
#1915000000
0&
#1920000000
b1001 >
1&
#1925000000
0&
#1930000000
b1010 >
1&
#1935000000
0&
#1940000000
0#
b100 <
b1011 >
1&
#1945000000
0&
#1950000000
02
b0 %
b0 4
b0 <
b1110 !
b1110 ;
b1 $
b1 :
1&
#1950200000
b11 -
b11 3
b11 ,
0(
#1955000000
0&
#1960000000
b0 >
1&
#1965000000
0&
#1970000000
1&
#1975000000
0&
#1980000000
1&
#1985000000
0&
#1990000000
1&
#1995000000
0&
#2000000000
1&
#2005000000
0&
#2010000000
1&
#2015000000
0&
#2020000000
1&
#2025000000
0&
#2030000000
1&
#2035000000
0&
#2040000000
1&
#2045000000
0&
#2050000000
1&
#2055000000
0&
#2060000000
1&
#2065000000
0&
#2070000000
1&
#2075000000
0&
#2080000000
1&
#2080200000
b1 -
b1 3
1*
b110 ,
#2085000000
0&
#2090000000
1#
b1 <
1&
#2090200000
1(
0*
#2095000000
0&
#2100000000
b1 >
1&
#2105000000
0&
#2110000000
b10 >
1&
#2115000000
0&
#2120000000
b11 >
1&
#2125000000
0&
#2130000000
b100 >
1&
#2135000000
0&
#2140000000
b101 >
1&
#2145000000
0&
#2150000000
b110 >
1&
#2155000000
0&
#2160000000
b111 >
1&
#2165000000
0&
#2170000000
b1000 >
1&
#2175000000
0&
#2180000000
b1001 >
1&
#2185000000
0&
#2190000000
b1010 >
1&
#2195000000
0&
#2200000000
0#
b100 <
b1011 >
1&
#2205000000
0&
#2210000000
b0 <
b1010 !
b1010 ;
b10 $
b10 :
1&
#2210200000
b11 -
b11 3
1*
b111 ,
0(
#2215000000
0&
#2220000000
b0 >
1#
b1 <
1&
#2220200000
1(
0*
#2225000000
0&
#2230000000
b1 >
1&
#2235000000
0&
#2240000000
b10 >
1&
#2245000000
0&
#2250000000
b11 >
1&
#2255000000
0&
#2260000000
b100 >
1&
#2265000000
0&
#2270000000
b101 >
1&
#2275000000
0&
#2280000000
b110 >
1&
#2285000000
0&
#2290000000
b111 >
1&
#2295000000
0&
#2300000000
b1000 >
1&
#2305000000
0&
#2310000000
b1001 >
1&
#2315000000
0&
#2320000000
b1010 >
1&
#2325000000
0&
#2330000000
0#
b100 <
b1011 >
1&
#2335000000
0&
#2340000000
b0 <
b10 !
b10 ;
b11 $
b11 :
1&
#2340200000
b10 -
b10 3
1*
b101 ,
0(
#2345000000
0&
#2350000000
b0 >
1#
b1 <
1&
#2350200000
1(
0*
#2355000000
0&
#2360000000
b1 >
1&
#2365000000
0&
#2370000000
b10 >
1&
#2375000000
0&
#2380000000
b11 >
1&
#2385000000
0&
#2390000000
b100 >
1&
#2395000000
0&
#2400000000
b101 >
1&
#2405000000
0&
#2410000000
b110 >
1&
#2415000000
0&
#2420000000
b111 >
1&
#2425000000
0&
#2430000000
b1000 >
1&
#2435000000
0&
#2440000000
b1001 >
1&
#2445000000
0&
#2450000000
b1010 >
1&
#2455000000
0&
#2460000000
0#
b100 <
b1011 >
1&
#2465000000
0&
#2470000000
11
b0 <
b0 !
b0 ;
b100 $
b100 :
1&
#2470200000
b0 -
b0 3
b0 ,
0(
#2475000000
0&
#2480000000
b0 >
1&
