control_fsm.v
`timescale 1ns / 100ps

// clock frequency : 1 KHz
// RESET siganl is active high

module control_fsm (entry_sensor, exit_sensor, vacant_parking,
				CLK , RESET,
				capacity, best_location, parkings, door_open_signal, full_signal);
    
    input entry_sensor, exit_sensor, CLK, RESET;
	input [1:0] vacant_parking;
	output reg door_open_signal, full_signal;
	output [2:0] capacity;
	output [1:0] best_location;
	output reg [3:0] parkings;

    // with 1KHz clock frequency we can count at most 63s 
	reg [15:0] timer;

    reg [1:0] state;
    parameter IDLE = 2'b00 , DOOR_OPEN = 2'b01 , FULL = 2'b10 , ASSIGN_PARKING = 2'b11;

    wire full, empty;

    assign full = parkings[0] & parkings[1] & parkings[2] & parkings[3];
	assign empty = ~(parkings[0] | parkings[1] | parkings[2] | parkings[3]);

    assign capacity[2] = empty;
    assign capacity[1] = ((~parkings[0] & ~parkings[1] & parkings[2]) |
                        (~parkings[1] & ~parkings[2] & parkings[3]) |
                        (parkings[0] & ~parkings[1] & ~parkings[3]) |
                        (parkings[1] & ~parkings[2] & ~parkings[3]) |
                        (~parkings[0] & parkings[1] & ~parkings[3]) |
                        (~parkings[0] & parkings[1] & ~parkings[2]));

    assign capacity[0] = ((parkings[1] ^ parkings[3]) | 
                        (parkings[0] ^ parkings[2]));

    // The case in which parkings is equal to 1111 is considered don't care
    assign best_location[1] = parkings[0] & parkings[1];
    assign best_location[0] = (((~parkings[1]) & parkings[0]) |
                                (parkings[2] & parkings[0]));
   		                      
    always @ (posedge CLK or posedge RESET) begin
        if (RESET) begin
            state = IDLE; // Initialize to IDLE
            parkings = 4'b0000;
            door_open_signal = 1'b0;
            full_signal = 1'b0;
        end 
        else begin
            // timer <= timer;  // Default assignments to prevent latches
            // state <= state;  // Default assignments to prevent latches
            case (state)
                IDLE : begin
    				timer <= 16'b0000000000000001;
                    if (entry_sensor & ~exit_sensor)
                        if (full) begin
                            state = FULL;
    						full_signal = 1'b1;
    					end
                        else begin
                            state = DOOR_OPEN;
	    					door_open_signal = 1'b1;
                        end
                    if (~entry_sensor & exit_sensor)
                        if (~empty) begin
                            state = DOOR_OPEN;
						    door_open_signal = 1'b1;
                        end
                end

                DOOR_OPEN : begin
			    	timer = timer + 1;
				    if (timer > 10 /*IT MUST BE 10000*/) begin
					    state = ASSIGN_PARKING;
    					door_open_signal = 1'b0;
	    			end
		    	 end

                FULL : begin 
				    timer = timer + 1;
    				if (timer > 3 /*IT MUST BE 3000*/) begin
	    				state = IDLE;
		    			full_signal = 1'b0;
			    	end
			    end

                ASSIGN_PARKING : begin 
	    			if (entry_sensor & ~exit_sensor) begin
		    			parkings[3] = parkings[3] |  (parkings[0] & parkings[1] & parkings[2]);
			    		parkings[2] = parkings[2] | (parkings[0] & parkings[1]);
				    	parkings[1] = parkings[1] | parkings[2];
					    parkings[0] = 1'b1;
				    end

    				if (~entry_sensor & exit_sensor) begin
	    				parkings[3] = parkings[3] & (~vacant_parking[0] | ~vacant_parking[1]);
		    			parkings[2] = parkings[2] & (~vacant_parking[0] | vacant_parking[1]);
			    		parkings[1] = parkings[1] & (vacant_parking[0] | ~vacant_parking[1]);
				    	parkings[0] = parkings[0] & (vacant_parking[0] | vacant_parking[1]);
				    end
                    state = IDLE;
			    end
            endcase
        end
    end                            

endmodule

control_fsm_test.v
`include "control_fsm.v"
`timescale 1us / 100ns

module control_fsm_test();

    wire door_open_signal, full_signal;
	wire [2:0] capacity;
	wire [1:0] best_location;
	wire [3:0] parkings;

    reg entry_sensor, exit_sensor, CLK, RESET;
	reg [1:0] vacant_parking;

    control_fsm fsm (entry_sensor, exit_sensor, vacant_parking,
				CLK , RESET,
				capacity, best_location, parkings, door_open_signal, full_signal);

    initial begin
        CLK = 1'b1;
        repeat (100) // 50 milisecond. 
            #500 CLK = ~CLK;
    end

    initial begin
        $dumpfile("control_fsm_test.vcd");
        $dumpvars(0, control_fsm_test);

        RESET = 1'b1; #10
        RESET = 1'b0; #10

        entry_sensor = 1'b1;
        exit_sensor = 1'b0; #1500;

        entry_sensor = 1'b0;
        exit_sensor = 1'b0;


        

    end

endmodule

control_fsm_test.vcd
$date
	Sat Dec 14 14:46:00 2024
$end
$version
	Icarus Verilog
$end
$timescale
	100ps
$end
$scope module control_fsm_test $end
$var wire 4 ! parkings [3:0] $end
$var wire 1 " full_signal $end
$var wire 1 # door_open_signal $end
$var wire 3 $ capacity [2:0] $end
$var wire 2 % best_location [1:0] $end
$var reg 1 & CLK $end
$var reg 1 ' RESET $end
$var reg 1 ( entry_sensor $end
$var reg 1 ) exit_sensor $end
$var reg 2 * vacant_parking [1:0] $end
$scope module fsm $end
$var wire 1 & CLK $end
$var wire 1 ' RESET $end
$var wire 1 + empty $end
$var wire 1 ( entry_sensor $end
$var wire 1 ) exit_sensor $end
$var wire 1 , full $end
$var wire 2 - vacant_parking [1:0] $end
$var wire 3 . capacity [2:0] $end
$var wire 2 / best_location [1:0] $end
$var parameter 2 0 ASSIGN_PARKING $end
$var parameter 2 1 DOOR_OPEN $end
$var parameter 2 2 FULL $end
$var parameter 2 3 IDLE $end
$var reg 1 # door_open_signal $end
$var reg 1 " full_signal $end
$var reg 4 4 parkings [3:0] $end
$var reg 2 5 state [1:0] $end
$var reg 16 6 timer [15:0] $end
$upscope $end
$upscope $end
$enddefinitions $end
$comment Show the parameter values. $end
$dumpall
b0 3
b10 2
b1 1
b11 0
$end
#0
$dumpvars
bx 6
b0 5
b0 4
b0 /
b100 .
bx -
0,
1+
bx *
x)
x(
1'
1&
b0 %
b100 $
0#
0"
b0 !
$end
#100000
0'
#200000
0)
1(
#5000000
0&
#10000000
b1 6
1#
b1 5
1&
#15000000
0&
#15200000
0(
#20000000
b10 6
1&
#25000000
0&
#30000000
b11 6
1&
#35000000
0&
#40000000
b100 6
1&
#45000000
0&
#50000000
b101 6
1&
#55000000
0&
#60000000
b110 6
1&
#65000000
0&
#70000000
b111 6
1&
#75000000
0&
#80000000
b1000 6
1&
#85000000
0&
#90000000
b1001 6
1&
#95000000
0&
#100000000
b1010 6
1&
#105000000
0&
#110000000
0#
b11 5
b1011 6
1&
#115000000
0&
#120000000
b0 5
1&
#125000000
0&
#130000000
b1 6
1&
