door_open_signal_control.v
`timescale 1ns / 100ps

// clock frequency : 2Hz

module door_open_signal_control(in_signal, CLK, out_signal);
    input in_signal, CLK;
    output out_signal;

    assign out_signal = in_signal & CLK;

endmodule

door_open_signal_control_test.v
`include "door_open_signal_control.v"
`timescale 1us / 100ns

module door_open_signal_control_test();

    reg in_signal, CLK;
    wire out_signal;

    door_open_signal_control control (in_signal, CLK, out_signal);

    initial begin
        CLK = 1'b1;
        repeat (1000) // 250 milisecond. 
            #250 CLK = ~CLK;
    end

    initial begin
        $dumpfile("door_open_signal_control_test.vcd");
        $dumpvars(0, door_open_signal_control_test);
        in_signal = 1'b0;
        #1000
        in_signal = 1'b1; 
        #10000
        in_signal = 1'b0;       
    end

endmodule

door_open_signal_control_test.vcd
$date
	Sat Dec 14 22:04:11 2024
$end
$version
	Icarus Verilog
$end
$timescale
	100ps
$end
$scope module door_open_signal_control_test $end
$var wire 1 ! out_signal $end
$var reg 1 " CLK $end
$var reg 1 # in_signal $end
$scope module control $end
$var wire 1 " CLK $end
$var wire 1 # in_signal $end
$var wire 1 ! out_signal $end
$upscope $end
$upscope $end
$enddefinitions $end
$comment Show the parameter values. $end
$dumpall
$end
#0
$dumpvars
0#
1"
0!
$end
#2500000
0"
#5000000
1"
#7500000
0"
#10000000
1!
1"
1#
#12500000
0!
0"
#15000000
1!
1"
#17500000
0!
0"
#20000000
1!
1"
#22500000
0!
0"
#25000000
1!
1"
#27500000
0!
0"
#30000000
1!
1"
#32500000
0!
0"
#35000000
1!
1"
#37500000
0!
0"
#40000000
1!
1"
#42500000
0!
0"
#45000000
1!
1"
#47500000
0!
0"
#50000000
1!
1"
#52500000
0!
0"
#55000000
1!
1"
#57500000
0!
0"
#60000000
1!
1"
#62500000
0!
0"
#65000000
1!
1"
#67500000
0!
0"
#70000000
1!
1"
#72500000
0!
0"
#75000000
1!
1"
#77500000
0!
0"
#80000000
1!
1"
#82500000
0!
0"
#85000000
1!
1"
#87500000
0!
0"
#90000000
1!
1"
#92500000
0!
0"
#95000000
1!
1"
#97500000
0!
0"
#100000000
1!
1"
#102500000
0!
0"
#105000000
1!
1"
#107500000
0!
0"
#110000000
1"
0#
