full_signal_control.v
// clock frequency : 1 Hz

module full_signal_control (in_signal, CLK, out_signal);

    input in_signal, CLK;
    output reg out_signal;

    reg [3:0] step;

    // It should alternate only three times
    always @ (posedge in_signal) begin
        step = 4'b0000;
    end

    always @ (CLK) begin
        if (step == 4'b0000) begin
            out_signal = in_signal;
            step = step + 1;
        end
        if (step < 8) begin
            out_signal = ~out_signal;
            step = step + 1;
        end
    end
endmodule

full_signal_control_test.v
`include "full_signal_control.v"
`timescale 1us / 100ns

module full_signal_control_test();

    reg in_signal, CLK;
    wire out_signal;

    full_signal_control test (in_signal, CLK, out_signal);

    initial begin
        CLK = 1'b1;
        repeat (100)
            #500 CLK = ~CLK;
    end

    initial begin
        $dumpfile("full_signal_control_test.vcd");
        $dumpvars(0, full_signal_control_test);
        in_signal = 1'b0;
        #800
        in_signal = 1'b1;
        #3000
        in_signal = 1'b0;
        #2000
        in_signal = 1'b1;
        #3000
        in_signal = 1'b0;
    end

endmodule

full_signal_control_test.vcd
$date
	Sun Dec 15 09:43:42 2024
$end
$version
	Icarus Verilog
$end
$timescale
	100ns
$end
$scope module full_signal_control_test $end
$var wire 1 ! out_signal $end
$var reg 1 " CLK $end
$var reg 1 # in_signal $end
$scope module test $end
$var wire 1 " CLK $end
$var wire 1 # in_signal $end
$var reg 1 ! out_signal $end
$var reg 4 $ step [3:0] $end
$upscope $end
$upscope $end
$enddefinitions $end
$comment Show the parameter values. $end
$dumpall
$end
#0
$dumpvars
bx $
0#
1"
x!
$end
#5000
0"
#8000
b0 $
1#
#10000
b10 $
0!
1"
#15000
b11 $
1!
0"
#20000
b100 $
0!
1"
#25000
b101 $
1!
0"
#30000
b110 $
0!
1"
#35000
b111 $
1!
0"
#38000
0#
#40000
b1000 $
0!
1"
#45000
0"
#50000
1"
#55000
0"
#58000
b0 $
1#
#60000
b10 $
0!
1"
#65000
b11 $
1!
0"
#70000
b100 $
0!
1"
#75000
b101 $
1!
0"
#80000
b110 $
0!
1"
#85000
b111 $
1!
0"
#88000
0#
#90000
b1000 $
0!
1"
